fastapi_rest_mongo-0.1.0.dist-info/METADATA
fastapi_rest_mongo-0.1.0.dist-info/WHEEL
fastapi_rest_mongo/__init__.py
fastapi_rest_mongo-0.1.0.dist-info/RECORD
